eletrica/__init__.py
eletrica-0.0.2.dist-info/LICENSE
eletrica-0.0.2.dist-info/METADATA
eletrica-0.0.2.dist-info/WHEEL
eletrica-0.0.2.dist-info/top_level.txt
eletrica-0.0.2.dist-info/RECORD
