Metadata-Version: 2.1
Name: eletrica
Version: 0.0.2
Summary: Módulo para auxiliar no cálculo de circuitos elétricos no domínio da frequência, através da implementação de classes e funções para tratamento de grandezas nos formatos retangular e polar, conforme os padrões utilizados em estudos de Engenharia Elétrica.
Home-page: https://github.com/allancavalari/eletrica
Author: Allan M. Cavalari
License-File: LICENSE
Requires-Dist: numpy
